toxicity_detector/__init__.py
toxicity_detector/app/__init__.py
toxicity_detector/app/agreement_tab.py
toxicity_detector/app/app.py
toxicity_detector/app/app_config_loader.py
toxicity_detector/app/config_tab.py
toxicity_detector/app/detection_tab.py
toxicity_detector/backend.py
toxicity_detector/chains.py
toxicity_detector/cli.py
toxicity_detector/config.py
toxicity_detector/datamodels.py
toxicity_detector/managers/__init__.py
toxicity_detector/managers/config_manager.py
toxicity_detector/package_data/__init__.py
toxicity_detector/package_data/default_pipeline_config.yaml
toxicity_detector/result.py
toxicity_detector-0.1.0.dist-info/WHEEL
toxicity_detector-0.1.0.dist-info/entry_points.txt
toxicity_detector-0.1.0.dist-info/METADATA
toxicity_detector-0.1.0.dist-info/RECORD
