Metadata-Version: 2.3
Name: toxicity-detector
Version: 0.1.0
Summary: An LLM-based pipeline to detect toxic speech.
Author: Sebastian Cacean
Author-email: Sebastian Cacean <sebastian.cacean@kit.edu>
Requires-Dist: huggingface-hub
Requires-Dist: langchain
Requires-Dist: langchain-core
Requires-Dist: langchain-huggingface
Requires-Dist: langchain-openai
Requires-Dist: gradio
Requires-Dist: python-dotenv
Requires-Dist: loguru
Requires-Python: >=3.12
